{"cameraMode":{"drawMode":0,"name":"Shaded","section":"Shading Mode"},"sceneLighting":false,"audioPlay":false,"sceneViewState":{"m_AlwaysRefresh":false,"showFog":true,"showSkybox":false,"showFlares":true,"showImageEffects":true,"showParticleSystems":true,"showVisualEffectGraphs":true,"m_FxEnabled":true},"in2DMode":false,"pivot":{"x":9.289999961853028,"y":0.8240000009536743,"z":-21.46500015258789},"rotation":{"x":0.37267476320266726,"y":-0.5152890682220459,"z":0.2649322748184204,"w":0.7248463034629822},"size":10.0,"orthographic":false}